cr_dbconnections/__init__.py
cr_dbconnections/admin_cadastro.py
cr_dbconnections/admin_loja.py
cr_dbconnections/app_mylist.py
cr_dbconnections/core_mongo.py
cr_dbconnections/core_relationalsql.py
cr_dbconnections/datawarehouse.py
cr_dbconnections/mongo_rd.py
cr_dbconnections-0.0.5.dist-info/METADATA
cr_dbconnections-0.0.5.dist-info/WHEEL
cr_dbconnections-0.0.5.dist-info/top_level.txt
cr_dbconnections-0.0.5.dist-info/RECORD
