Metadata-Version: 2.1
Name: cr-dbconnections
Version: 0.0.5
Summary: Classes básicas de conexão com bancos de dados.
Home-page: https://github.com/ConsultaRemedios/cr_dbconnections
Author: Henrique Ortiz
Author-email: henrique.ortiz@consultaremedios.com.br
License: UNKNOWN
Platform: UNKNOWN
Classifier: Programming Language :: Python :: 3
Classifier: License :: OSI Approved :: MIT License
Classifier: Operating System :: OS Independent
Requires-Dist: pymongo
Requires-Dist: sqlalchemy
Requires-Dist: python-dotenv
Requires-Dist: PyYAML
